ansipython/ANSI.py
ansipython/Back.py
ansipython/Fore.py
ansipython/__init__.py
ansipython-0.0.0.1.dist-info/LICENSE
ansipython-0.0.0.1.dist-info/METADATA
ansipython-0.0.0.1.dist-info/WHEEL
ansipython-0.0.0.1.dist-info/top_level.txt
ansipython-0.0.0.1.dist-info/RECORD
