Metadata-Version: 2.1
Name: ansipython
Version: 0.0.0.1
Summary: ANSI escape codes in python
Home-page: https://github.com/Dragon-Batch/macropython
License: UNKNOWN
Platform: UNKNOWN
Classifier: Programming Language :: Python :: 3
Classifier: License :: OSI Approved :: MIT License
Classifier: Operating System :: OS Independent
Requires-Python: >=3.10
License-File: LICENSE
